LICENSE
README.md
setup.py
tsb_encoder_decoder/tsb.py
tsb_encoder_decoder.egg-info/PKG-INFO
tsb_encoder_decoder.egg-info/SOURCES.txt
tsb_encoder_decoder.egg-info/dependency_links.txt
tsb_encoder_decoder.egg-info/requires.txt
tsb_encoder_decoder.egg-info/top_level.txt