Metadata-Version: 2.1
Name: tsb-encoder-decoder
Version: 0.1.0
Summary: Encodes and decodes TSB messages
Author: cristophvigneri
Author-email: cristophvigneri@gmail.com
Classifier: Programming Language :: Python :: 3
Classifier: License :: OSI Approved :: MIT License
Classifier: Operating System :: OS Independent
License-File: LICENSE
